equiforge/__init__.py
equiforge/_version.py
equiforge/converters/__init__.py
equiforge/converters/equi2pers.py
equiforge/converters/pers2equi.py
equiforge/utils/__init__.py
equiforge/utils/logging_utils.py
equiforge/utils/projection_utils.py
equiforge/utils/sampling.py
equiforge-0.2.0.dist-info/licenses/LICENSE
equiforge-0.2.0.dist-info/METADATA
equiforge-0.2.0.dist-info/WHEEL
equiforge-0.2.0.dist-info/top_level.txt
equiforge-0.2.0.dist-info/RECORD
