Metadata-Version: 2.4
Name: EquiForge
Version: 0.2.0
Summary: A toolkit for equirectangular image processing and conversions.
Author-email: Mikkel Kappel Persson <mikkelkp@hotmail.com>
Project-URL: Homepage, https://github.com/mikkelkappelpersson/equiforge
Keywords: equirectangular,panorama,image processing,360
Classifier: Development Status :: 3 - Alpha
Classifier: Intended Audience :: Developers
Classifier: Programming Language :: Python :: 3.8
Classifier: Programming Language :: Python :: 3.9
Classifier: Programming Language :: Python :: 3.10
Classifier: Programming Language :: Python :: 3.11
Classifier: License :: OSI Approved :: Apache Software License
Requires-Python: >=3.8
License-File: LICENSE
Requires-Dist: numpy>=1.20.0
Requires-Dist: numba>=0.53.0
Requires-Dist: Pillow>=8.0.0
Provides-Extra: dev
Requires-Dist: pytest>=6.0.0; extra == "dev"
Requires-Dist: jupyter>=1.0.0; extra == "dev"
Requires-Dist: matplotlib>=3.4.0; extra == "dev"
Requires-Dist: matplotlib>=3.4.0; extra == "dev"
Dynamic: license-file
